revo/__init__.py
revo/_revo.py
revo-0.2.3.dist-info/LICENSE
revo-0.2.3.dist-info/METADATA
revo-0.2.3.dist-info/WHEEL
revo-0.2.3.dist-info/top_level.txt
revo-0.2.3.dist-info/RECORD
