Metadata-Version: 2.1
Name: revo
Version: 0.2.3
Summary: Referenced Values in Objects.
Author-email: Sun Yijiang <sunyijiang@gmail.com>
Project-URL: Homepage, https://github.com/sunyj/revo
Project-URL: Bug Tracker, https://github.com/sunyj/revo/issues
Classifier: Programming Language :: Python :: 3
Classifier: License :: OSI Approved :: MIT License
Classifier: Operating System :: OS Independent
Requires-Python: >=3.4
License-File: LICENSE
